visier/__init__.py
visier/sdk/__init__.py
visier/sdk/api/__init__.py
visier/sdk/api/data_out/__init__.py
visier/sdk/api/data_out/api_client.py
visier/sdk/api/data_out/api_response.py
visier/sdk/api/data_out/configuration.py
visier/sdk/api/data_out/exceptions.py
visier/sdk/api/data_out/py.typed
visier/sdk/api/data_out/rest.py
visier/sdk/api/data_out/api/__init__.py
visier/sdk/api/data_out/api/data_query_api.py
visier/sdk/api/data_out/api/data_version_export_api.py
visier/sdk/api/data_out/api/search_api.py
visier/sdk/api/data_out/api/vee_api.py
visier/sdk/api/data_out/api/vee_query_api.py
visier/sdk/api/data_out/models/__init__.py
visier/sdk/api/data_out/models/aggregation_query_dto.py
visier/sdk/api/data_out/models/aggregation_query_execution_dto.py
visier/sdk/api/data_out/models/aggregation_query_source_dto.py
visier/sdk/api/data_out/models/aggregation_query_source_metric_dto.py
visier/sdk/api/data_out/models/aggregation_query_source_metrics_dto.py
visier/sdk/api/data_out/models/aggregation_type_parameter_value_dto.py
visier/sdk/api/data_out/models/cell_distribution_bin_dto.py
visier/sdk/api/data_out/models/cell_distribution_options_dto.py
visier/sdk/api/data_out/models/cell_dto.py
visier/sdk/api/data_out/models/cell_set_axis_dto.py
visier/sdk/api/data_out/models/cell_set_axis_position_dto.py
visier/sdk/api/data_out/models/cell_set_dto.py
visier/sdk/api/data_out/models/cohort_filter_dto.py
visier/sdk/api/data_out/models/data_version_export_column_dto.py
visier/sdk/api/data_out/models/data_version_export_data_version_summary_dto.py
visier/sdk/api/data_out/models/data_version_export_data_versions_dto.py
visier/sdk/api/data_out/models/data_version_export_dto.py
visier/sdk/api/data_out/models/data_version_export_file_dto.py
visier/sdk/api/data_out/models/data_version_export_job_status_dto.py
visier/sdk/api/data_out/models/data_version_export_part_file_dto.py
visier/sdk/api/data_out/models/data_version_export_schedule_job_request_dto.py
visier.sdk.api.data_out-22222222.99201.1456.dist-info/METADATA
visier.sdk.api.data_out-22222222.99201.1456.dist-info/WHEEL
visier.sdk.api.data_out-22222222.99201.1456.dist-info/top_level.txt
visier.sdk.api.data_out-22222222.99201.1456.dist-info/RECORD
